packet/BGPConfig.py
packet/BGPSession.py
packet/Batch.py
packet/Device.py
packet/DeviceBatch.py
packet/Email.py
packet/Event.py
packet/Facility.py
packet/HardwareReservation.py
packet/IPAddress.py
packet/Manager.py
packet/Metro.py
packet/OperatingSystem.py
packet/Organization.py
packet/Plan.py
packet/Project.py
packet/Provider.py
packet/SSHKey.py
packet/Snapshot.py
packet/Vlan.py
packet/Volume.py
packet/__init__.py
packet/baseapi.py
packet_python-1.44.3.dist-info/LICENSE.txt
packet_python-1.44.3.dist-info/METADATA
packet_python-1.44.3.dist-info/WHEEL
packet_python-1.44.3.dist-info/top_level.txt
packet_python-1.44.3.dist-info/RECORD
